milolib/__init__.py
milolib/modulo.py
milolib-0.1.1.dist-info/METADATA
milolib-0.1.1.dist-info/WHEEL
milolib-0.1.1.dist-info/top_level.txt
milolib-0.1.1.dist-info/RECORD
